MeshAnim/__init__.py
MeshAnim/animate.py
MeshAnim/frames.py
MeshAnim/time_series.py
MeshAnim-0.1.5.dist-info/LICENSE
MeshAnim-0.1.5.dist-info/METADATA
MeshAnim-0.1.5.dist-info/WHEEL
MeshAnim-0.1.5.dist-info/top_level.txt
MeshAnim-0.1.5.dist-info/RECORD
