Metadata-Version: 2.1
Name: MeshAnim
Version: 0.1.5
Summary: Meshes animations
Home-page: https://gitlab.inria.fr/gdesrues1/MeshAnim
Author: Gaetan Desrues
Author-email: gaetan.desrues@inria.fr
License: UNKNOWN
Platform: UNKNOWN
Classifier: Programming Language :: Python :: 3
Classifier: License :: OSI Approved :: MIT License
Classifier: Operating System :: OS Independent
License-File: LICENSE
